{
  "id": 2,
  "fecha": "2026-01-02 15:39:26",
  "items": [
    {
      "cantidad": 1,
      "nombre": "AGUA CRISTAL 200ML",
      "subtotal": 1500.0
    }
  ],
  "total": 1500.0,
  "cliente": {
    "nombre": "CONTADO",
    "identificacion": "",
    "telefono": "",
    "email": "",
    "direccion": "Venta sin registro de cliente",
    "puntos": 0
  },
  "metodo_pago": {
    "tipo": "efectivo",
    "monto_efectivo": 1500,
    "monto_transferencia": 0,
    "monto_recibido": 1500,
    "cambio": 0
  },
  "config_moneda": {
    "simbolo": "$",
    "separador_miles": ".",
    "separador_decimales": ",",
    "decimales": 0
  },
  "empresa": {
    "nombre": "TIENDA - POS BAUSSA",
    "nit": "123456789-12",
    "direccion": "Calle Principal #123",
    "telefono": "300 928 8888"
  }
}